my_kyivstar.py
my_kyivstar-0.0.3.dist-info/LICENSE
my_kyivstar-0.0.3.dist-info/METADATA
my_kyivstar-0.0.3.dist-info/WHEEL
my_kyivstar-0.0.3.dist-info/entry_points.txt
my_kyivstar-0.0.3.dist-info/top_level.txt
my_kyivstar-0.0.3.dist-info/RECORD
