Metadata-Version: 2.1
Name: my-kyivstar
Version: 0.0.3
Summary: Check balance using cli from account.kyivstar.ua
Home-page: https://github.com/vgavro/my-kyivstar
Author: Victor Gavro
Author-email: vgavro@gmail.com
License: MIT License
Platform: UNKNOWN
Classifier: Development Status :: 3 - Alpha
Classifier: License :: OSI Approved :: MIT License
Classifier: Operating System :: OS Independent
Classifier: Programming Language :: Python
Classifier: Programming Language :: Python :: 3.6
Requires-Dist: requests
Requires-Dist: requests-toolbelt
Requires-Dist: lxml
Requires-Dist: cssselect
Requires-Dist: pyyaml
